Workbook

Sheet Dashboard

Sheet Summary
B2: Profit Leaks
B4: Sub-category with negative profit
B5: Sub-category | C5: Category | D5: Revenue | E5: Profit | F5: Qty_sold | G5: Profit_margin
B6: Leggings | C6: Clothing | D6: 2106 | E6: -130 | F6: 186 | G6: -0.061728395
B7: Skirt | C7: Clothing | D7: 1946 | E7: -315 | F7: 248 | G7: -0.1618705
B8: Kurti | C8: Clothing | D8: 3361 | E8: -401 | F8: 164 | G8: -0.11930973
B9: Electronic Games | C9: Electronics | D9: 39168 | E9: -644 | F9: 297 | G9: -0.016441993
B10: Furnishings | C10: Furniture | D10: 13484 | E10: -806 | F10: 310 | G10: -0.059774548
B12: Identifying Profit Leak from Payment Method
B13: Payment Method | C13: Negative Profit | D13: Profit | E13: Count Of -ve Order_ID | F13: Ttl Order-Id | G13: Failure Margin
B14: COD | C14: =SUMIFS(Details_cleaned_work!C:C,Details_cleaned_work!G:G,$B14,Details_cleaned_work!C:C,"<0") -> -15483 | D14: =SUMIFS(Details_cleaned_work!C:C,Details_cleaned_work!G:G,$B14,Details_cleaned_work!C:C,">0") -> 28030 | E14: =COUNTIFS(Details_cleaned_work!A:A,"<>",Details_cleaned_work!C:C,"<0",Details_cleaned_work!G:G,Summary!B14) -> 244 | F14: =COUNTIF(Details_cleaned_work!G:G,Summary!B14) -> 684 | G14: =E14/F14 -> 0.35672515
B15: UPI | C15: =SUMIFS(Details_cleaned_work!C:C,Details_cleaned_work!G:G,$B15,Details_cleaned_work!C:C,"<0") -> -7103 | D15: =SUMIFS(Details_cleaned_work!C:C,Details_cleaned_work!G:G,$B15,Details_cleaned_work!C:C,">0") -> 10389 | E15: =COUNTIFS(Details_cleaned_work!A:A,"<>",Details_cleaned_work!C:C,"<0",Details_cleaned_work!G:G,Summary!B15) -> 123 | F15: =COUNTIF(Details_cleaned_work!G:G,Summary!B15) -> 331 | G15: =E15/F15 -> 0.37160121
B16: EMI | C16: =SUMIFS(Details_cleaned_work!C:C,Details_cleaned_work!G:G,$B16,Details_cleaned_work!C:C,"<0") -> -5958 | D16: =SUMIFS(Details_cleaned_work!C:C,Details_cleaned_work!G:G,$B16,Details_cleaned_work!C:C,">0") -> 10782 | E16: =COUNTIFS(Details_cleaned_work!A:A,"<>",Details_cleaned_work!C:C,"<0",Details_cleaned_work!G:G,Summary!B16) -> 41 | F16: =COUNTIF(Details_cleaned_work!G:G,Summary!B16) -> 120 | G16: =E16/F16 -> 0.34166667
B17: Credit Card | C17: =SUMIFS(Details_cleaned_work!C:C,Details_cleaned_work!G:G,$B17,Details_cleaned_work!C:C,"<0") -> -5632 | D17: =SUMIFS(Details_cleaned_work!C:C,Details_cleaned_work!G:G,$B17,Details_cleaned_work!C:C,">0") -> 18244 | E17: =COUNTIFS(Details_cleaned_work!A:A,"<>",Details_cleaned_work!C:C,"<0",Details_cleaned_work!G:G,Summary!B17) -> 57 | F17: =COUNTIF(Details_cleaned_work!G:G,Summary!B17) -> 163 | G17: =E17/F17 -> 0.34969325
B18: Debit Card | C18: =SUMIFS(Details_cleaned_work!C:C,Details_cleaned_work!G:G,$B18,Details_cleaned_work!C:C,"<0") -> -3903 | D18: =SUMIFS(Details_cleaned_work!C:C,Details_cleaned_work!G:G,$B18,Details_cleaned_work!C:C,">0") -> 7597 | E18: =COUNTIFS(Details_cleaned_work!A:A,"<>",Details_cleaned_work!C:C,"<0",Details_cleaned_work!G:G,Summary!B18) -> 64 | F18: =COUNTIF(Details_cleaned_work!G:G,Summary!B18) -> 202 | G18: =E18/F18 -> 0.31683168
B21: Key Insights
B22: 1 | C22: Clothings category has the highest profit leak and also profit margin when summed.
B23: 2 | C23: COD is the most used payment method
B24: 3 | C24: COD has highest amount of transactions that led to profit leaks (244)
B25: 4 | C25: UPI had the hghestfailure margin i.e the ratio of orders processed with negative profit to total orders processed (37.16%).
B26: 5 | C26: Comparing the negative order count to the total orders, an increasing rate of usage of UPI will yield high negative orders
B29: Recommendations
B30: Products
B31: 1 | C31: For profit leaks sub-categories, audit the cost of each item and increase the selling price
B32: 2 | C32: For already profitable sub-categories, create a floor price that must not be exceeded even when discounts are given in order to maintain profitability and also recover loses for other sub-categories
B33: 3 | C33: Also, drive focus to best selling categories. Increase products variety and invest in marketing and advertisement since its already a high demand and selling product
B34: Payment Options
B35: 1 | C35: For COD, increae tax or fee for each delivery.
B36: 2 | C36: For UPI, renegotiate with UPI gateway provider and cross check taxes
B37: 3 | C37: Since Credit Card is the best performer, offer a discount on purchases paid with credit card. This way, more orders will be placed using credits cards instead of COD or UPI.

Sheet Calculations
B2: Total revenue | C2: =GETPIVOTDATA("Sum of amount",'Pivot Tables'!$A$3) -> 437771 | H2: Row Labels | I2: Sum of amount | J2: Sum of profit | K2: Sum of quantity | L2: Sum of Profit Margin | M2: quantity_rank | N2: profit_rank | O2: rank_gap
B3: Net Profit | C3: =GETPIVOTDATA("Sum of profit",'Pivot Tables'!$A$3) -> 36963 | H3: Tables | I3: 22614 | J3: 3139 | K3: 61 | L3: 0.13880782 | M3: =_xlfn.RANK.EQ(K3,$K$3:$K$19,0) -> 17 | N3: =_xlfn.RANK.EQ(Table2[[#This Row],[Sum of profit]],Table2[Sum of profit],0) -> 5 | O3: =Table2[[#This Row],[quantity_rank]]-Table2[[#This Row],[profit_rank]] -> 12
B4: Profit Margin | C4: =GETPIVOTDATA("Sum of Profit Margin",'Pivot Tables'!$A$3) -> 0.084434556 | H4: Trousers | I4: 30039 | J4: 2847 | K4: 135 | L4: 0.09477679 | M4: =_xlfn.RANK.EQ(K4,$K$3:$K$19,0) -> 16 | N4: =_xlfn.RANK.EQ(Table2[[#This Row],[Sum of profit]],Table2[Sum of profit],0) -> 6 | O4: =Table2[[#This Row],[quantity_rank]]-Table2[[#This Row],[profit_rank]] -> 10
B5: Total Quantity Sold | C5: =GETPIVOTDATA("Sum of quantity",'Pivot Tables'!$A$3) -> 5615 | H5: Printers | I5: 59252 | J5: 8606 | K5: 291 | L5: 0.14524404 | M5: =_xlfn.RANK.EQ(K5,$K$3:$K$19,0) -> 9 | N5: =_xlfn.RANK.EQ(Table2[[#This Row],[Sum of profit]],Table2[Sum of profit],0) -> 1 | O5: =Table2[[#This Row],[quantity_rank]]-Table2[[#This Row],[profit_rank]] -> 8
B6: Total Unique Orders | C6: =COUNTA(_xlfn.UNIQUE(Details_cleaned_work!A2:A1501)) -> 500 | H6: Accessories | I6: 21728 | J6: 3353 | K6: 262 | L6: 0.15431701 | M6: =_xlfn.RANK.EQ(K6,$K$3:$K$19,0) -> 12 | N6: =_xlfn.RANK.EQ(Table2[[#This Row],[Sum of profit]],Table2[Sum of profit],0) -> 4 | O6: =Table2[[#This Row],[quantity_rank]]-Table2[[#This Row],[profit_rank]] -> 8
B7: Average Oeder Value | C7: =C2/C6 -> 875.542 | H7: Bookcases | I7: 56861 | J7: 6516 | K7: 297 | L7: 0.11459524 | M7: =_xlfn.RANK.EQ(K7,$K$3:$K$19,0) -> 7 | N7: =_xlfn.RANK.EQ(Table2[[#This Row],[Sum of profit]],Table2[Sum of profit],0) -> 2 | O7: =Table2[[#This Row],[quantity_rank]]-Table2[[#This Row],[profit_rank]] -> 5
H8: Leggings | I8: 2106 | J8: -130 | K8: 186 | L8: -0.061728395 | M8: =_xlfn.RANK.EQ(K8,$K$3:$K$19,0) -> 14 | N8: =_xlfn.RANK.EQ(Table2[[#This Row],[Sum of profit]],Table2[Sum of profit],0) -> 13 | O8: =Table2[[#This Row],[quantity_rank]]-Table2[[#This Row],[profit_rank]] -> 1
A9: Profit Loss by payment methods | B9: COD | C9: =SUMIFS(Details_cleaned_work!C:C,Details_cleaned_work!G:G,$B9,Details_cleaned_work!C:C,"<0") -> -15483 | D9: =SUMIFS(Details_cleaned_work!C:C,Details_cleaned_work!G:G,$B9,Details_cleaned_work!C:C,">0") -> 28030 | H9: Chairs | I9: 34222 | J9: 1627 | K9: 277 | L9: 0.047542517 | M9: =_xlfn.RANK.EQ(K9,$K$3:$K$19,0) -> 10 | N9: =_xlfn.RANK.EQ(Table2[[#This Row],[Sum of profit]],Table2[Sum of profit],0) -> 10 | O9: =Table2[[#This Row],[quantity_rank]]-Table2[[#This Row],[profit_rank]] -> 0
B10: UPI | C10: =SUMIFS(Details_cleaned_work!C:C,Details_cleaned_work!G:G,$B10,Details_cleaned_work!C:C,"<0") -> -7103 | D10: =SUMIFS(Details_cleaned_work!C:C,Details_cleaned_work!G:G,$B10,Details_cleaned_work!C:C,">0") -> 10389 | H10: Shirt | I10: 7555 | J10: 1513 | K10: 271 | L10: 0.20026473 | M10: =_xlfn.RANK.EQ(K10,$K$3:$K$19,0) -> 11 | N10: =_xlfn.RANK.EQ(Table2[[#This Row],[Sum of profit]],Table2[Sum of profit],0) -> 11 | O10: =Table2[[#This Row],[quantity_rank]]-Table2[[#This Row],[profit_rank]] -> 0
B11: EMI | C11: =SUMIFS(Details_cleaned_work!C:C,Details_cleaned_work!G:G,$B11,Details_cleaned_work!C:C,"<0") -> -5958 | D11: =SUMIFS(Details_cleaned_work!C:C,Details_cleaned_work!G:G,$B11,Details_cleaned_work!C:C,">0") -> 10782 | H11: Kurti | I11: 3361 | J11: -401 | K11: 164 | L11: -0.11930973 | M11: =_xlfn.RANK.EQ(K11,$K$3:$K$19,0) -> 15 | N11: =_xlfn.RANK.EQ(Table2[[#This Row],[Sum of profit]],Table2[Sum of profit],0) -> 15 | O11: =Table2[[#This Row],[quantity_rank]]-Table2[[#This Row],[profit_rank]] -> 0
B12: Credit Card | C12: =SUMIFS(Details_cleaned_work!C:C,Details_cleaned_work!G:G,$B12,Details_cleaned_work!C:C,"<0") -> -5632 | D12: =SUMIFS(Details_cleaned_work!C:C,Details_cleaned_work!G:G,$B12,Details_cleaned_work!C:C,">0") -> 18244 | H12: Skirt | I12: 1946 | J12: -315 | K12: 248 | L12: -0.1618705 | M12: =_xlfn.RANK.EQ(K12,$K$3:$K$19,0) -> 13 | N12: =_xlfn.RANK.EQ(Table2[[#This Row],[Sum of profit]],Table2[Sum of profit],0) -> 14 | O12: =Table2[[#This Row],[quantity_rank]]-Table2[[#This Row],[profit_rank]] -> -1
B13: Debit Card | C13: =SUMIFS(Details_cleaned_work!C:C,Details_cleaned_work!G:G,$B13,Details_cleaned_work!C:C,"<0") -> -3903 | D13: =SUMIFS(Details_cleaned_work!C:C,Details_cleaned_work!G:G,$B13,Details_cleaned_work!C:C,">0") -> 7597 | H13: Saree | I13: 59094 | J13: 4057 | K13: 795 | L13: 0.068653332 | M13: =_xlfn.RANK.EQ(K13,$K$3:$K$19,0) -> 1 | N13: =_xlfn.RANK.EQ(Table2[[#This Row],[Sum of profit]],Table2[Sum of profit],0) -> 3 | O13: =Table2[[#This Row],[quantity_rank]]-Table2[[#This Row],[profit_rank]] -> -2
H14: Phones | I14: 46119 | J14: 1847 | K14: 304 | L14: 0.04004857 | M14: =_xlfn.RANK.EQ(K14,$K$3:$K$19,0) -> 6 | N14: =_xlfn.RANK.EQ(Table2[[#This Row],[Sum of profit]],Table2[Sum of profit],0) -> 8 | O14: =Table2[[#This Row],[quantity_rank]]-Table2[[#This Row],[profit_rank]] -> -2
H15: Stole | I15: 18546 | J15: 2431 | K15: 671 | L15: 0.13107948 | M15: =_xlfn.RANK.EQ(K15,$K$3:$K$19,0) -> 3 | N15: =_xlfn.RANK.EQ(Table2[[#This Row],[Sum of profit]],Table2[Sum of profit],0) -> 7 | O15: =Table2[[#This Row],[quantity_rank]]-Table2[[#This Row],[profit_rank]] -> -4
H16: Handkerchief | I16: 14294 | J16: 1823 | K16: 741 | L16: 0.12753603 | M16: =_xlfn.RANK.EQ(K16,$K$3:$K$19,0) -> 2 | N16: =_xlfn.RANK.EQ(Table2[[#This Row],[Sum of profit]],Table2[Sum of profit],0) -> 9 | O16: =Table2[[#This Row],[quantity_rank]]-Table2[[#This Row],[profit_rank]] -> -7
H17: T-shirt | I17: 7382 | J17: 1500 | K17: 305 | L17: 0.20319697 | M17: =_xlfn.RANK.EQ(K17,$K$3:$K$19,0) -> 5 | N17: =_xlfn.RANK.EQ(Table2[[#This Row],[Sum of profit]],Table2[Sum of profit],0) -> 12 | O17: =Table2[[#This Row],[quantity_rank]]-Table2[[#This Row],[profit_rank]] -> -7
H18: Electronic Games | I18: 39168 | J18: -644 | K18: 297 | L18: -0.016441993 | M18: =_xlfn.RANK.EQ(K18,$K$3:$K$19,0) -> 7 | N18: =_xlfn.RANK.EQ(Table2[[#This Row],[Sum of profit]],Table2[Sum of profit],0) -> 16 | O18: =Table2[[#This Row],[quantity_rank]]-Table2[[#This Row],[profit_rank]] -> -9
H19: Furnishings | I19: 13484 | J19: -806 | K19: 310 | L19: -0.059774548 | M19: =_xlfn.RANK.EQ(K19,$K$3:$K$19,0) -> 4 | N19: =_xlfn.RANK.EQ(Table2[[#This Row],[Sum of profit]],Table2[Sum of profit],0) -> 17 | O19: =Table2[[#This Row],[quantity_rank]]-Table2[[#This Row],[profit_rank]] -> -13

Sheet PT_Charts
A3: Row Labels | B3: Sum of profit | D3: Row Labels | E3: Sum of profit | F3: Sum of quantity
A4: Accessories | B4: 3353 | D4: Clothing | E4: 13325 | F4: 3516
A5: Bookcases | B5: 6516 | D5: Electronics | E5: 13162 | F5: 1154
A6: Printers | B6: 8606 | D6: Furniture | E6: 10476 | F6: 945
A7: Saree | B7: 4057 | D7: Grand Total | E7: 36963 | F7: 5615
A8: Tables | B8: 3139
A9: Grand Total | B9: 25671
D10: Row Labels | E10: Sum of profit | F10: Sum of quantity
D11: COD | E11: 12547 | F11: 2456
D12: Credit Card | E12: 12612 | F12: 672
D13: Debit Card | E13: 3694 | F13: 741
D14: EMI | E14: 4824 | F14: 589
D15: UPI | E15: 3286 | F15: 1157
D16: Grand Total | E16: 36963 | F16: 5615
D19: Row Labels | E19: Sum of profit | G19: Row Labels | H19: Sum of quantity
D20: Bookcases | E20: 6516 | G20: Handkerchief | H20: 741
D21: Printers | E21: 8606 | G21: Saree | H21: 795
D22: Saree | E22: 4057 | G22: Stole | H22: 671
D23: Grand Total | E23: 19179 | G23: Grand Total | H23: 2207

Sheet Pivot Tables
A1: category | B1: (All)
A2: b | H2: c
A3: Row Labels | B3: Sum of amount | C3: Sum of profit | D3: Sum of quantity | E3: Sum of Profit Margin | H3: Row Labels | I3: Count of order_id | J3: Sum of amount | K3: Average of amount | L3: Sum of profit | M3: Average of Profit Margin | P3: Row Labels | Q3: Sum of amount | R3: Sum of profit | S3: Count of quantity
A4: Printers | B4: 59252 | C4: 8606 | D4: 291 | E4: 0.14524404 | H4: EMI | I4: 120 | J4: 77881 | K4: 649.00833 | L4: 4824 | M4: 0.061940653 | P4: B-25601 | Q4: 1429 | R4: 1078 | S4: 4
A5: Bookcases | B5: 56861 | C5: 6516 | D5: 297 | E5: 0.11459524 | H5: Credit Card | I5: 163 | J5: 86932 | K5: 533.32515 | L5: 12612 | M5: 0.14507891 | P5: B-25602 | Q5: 3889 | R5: 975 | S5: 5
A6: Saree | B6: 59094 | C6: 4057 | D6: 795 | E6: 0.068653332 | H6: Debit Card | I6: 202 | J6: 49136 | K6: 243.24752 | L6: 3694 | M6: 0.075179095 | P6: B-25603 | Q6: 2025 | R6: -180 | S6: 8
A7: Accessories | B7: 21728 | C7: 3353 | D7: 262 | E7: 0.15431701 | H7: COD | I7: 684 | J7: 155181 | K7: 226.87281 | L7: 12547 | M7: 0.080853971 | P7: B-25604 | Q7: 222 | R7: 22 | S7: 2
A8: Tables | B8: 22614 | C8: 3139 | D8: 61 | E8: 0.13880782 | H8: UPI | I8: 331 | J8: 68641 | K8: 207.37462 | L8: 3286 | M8: 0.047872263 | P8: B-25605 | Q8: 75 | R8: 0 | S8: 1
A9: Trousers | B9: 30039 | C9: 2847 | D9: 135 | E9: 0.09477679 | H9: Grand Total | I9: 1500 | J9: 437771 | K9: 291.84733 | L9: 36963 | M9: 0.084434556 | P9: B-25606 | Q9: 87 | R9: 4 | S9: 1
A10: Stole | B10: 18546 | C10: 2431 | D10: 671 | E10: 0.13107948 | P10: B-25607 | Q10: 50 | R10: -15 | S10: 1
A11: Phones | B11: 46119 | C11: 1847 | D11: 304 | E11: 0.04004857 | H11: a | P11: B-25608 | Q11: 2953 | R11: 2272 | S11: 4
A12: Handkerchief | B12: 14294 | C12: 1823 | D12: 741 | E12: 0.12753603 | H12: Row Labels | I12: Sum of amount | J12: Sum of profit | K12: Sum of quantity | L12: Average of Profit Margin | P12: B-25609 | Q12: 734 | R12: 24 | S12: 2
A13: Chairs | B13: 34222 | C13: 1627 | D13: 277 | E13: 0.047542517 | H13: Clothing | I13: 144323 | J13: 13325 | K13: 3516 | L13: 0.092327626 | P13: B-25610 | Q13: 2105 | R13: 442 | S13: 6
A14: Shirt | B14: 7555 | C14: 1513 | D14: 271 | E14: 0.20026473 | H14: Electronics | I14: 166267 | J14: 13162 | K14: 1154 | L14: 0.07916183 | P14: B-25611 | Q14: 160 | R14: -59 | S14: 1
A15: T-shirt | B15: 7382 | C15: 1500 | D15: 305 | E15: 0.20319697 | H15: Furniture | I15: 127181 | J15: 10476 | K15: 945 | L15: 0.082370794 | P15: B-25612 | Q15: 259 | R15: -55 | S15: 1
A16: Leggings | B16: 2106 | C16: -130 | D16: 186 | E16: -0.061728395 | H16: Grand Total | I16: 437771 | J16: 36963 | K16: 5615 | L16: 0.084434556 | P16: B-25613 | Q16: 1603 | R16: 0 | S16: 1
A17: Skirt | B17: 1946 | C17: -315 | D17: 248 | E17: -0.1618705 | P17: B-25614 | Q17: 592 | R17: 42 | S17: 2
A18: Kurti | B18: 3361 | C18: -401 | D18: 164 | E18: -0.11930973 | P18: B-25615 | Q18: 68 | R18: 20 | S18: 1
A19: Electronic Games | B19: 39168 | C19: -644 | D19: 297 | E19: -0.016441993 | H19: Row Labels | I19: Count of order_id | J19: Sum of amount | K19: Average of amount | L19: Sum of profit | M19: Average of Profit Margin | P19: B-25616 | Q19: 194 | R19: -48 | S19: 4
A20: Furnishings | B20: 13484 | C20: -806 | D20: 310 | E20: -0.059774548 | H20: Credit Card | I20: 163 | J20: 86932 | K20: 533.32515 | L20: 12612 | M20: 0.14507891 | P20: B-25617 | Q20: 305 | R20: -270 | S20: 1
A21: Grand Total | B21: 437771 | C21: 36963 | D21: 5615 | E21: 0.084434556 | H21: COD | I21: 684 | J21: 155181 | K21: 226.87281 | L21: 12547 | M21: 0.080853971 | P21: B-25618 | Q21: 374 | R21: 127 | S21: 2
H22: Debit Card | I22: 202 | J22: 49136 | K22: 243.24752 | L22: 3694 | M22: 0.075179095 | P22: B-25619 | Q22: 353 | R22: 90 | S22: 1
H23: EMI | I23: 120 | J23: 77881 | K23: 649.00833 | L23: 4824 | M23: 0.061940653 | P23: B-25620 | Q23: 193 | R23: 46 | S23: 1
H24: UPI | I24: 331 | J24: 68641 | K24: 207.37462 | L24: 3286 | M24: 0.047872263 | P24: B-25621 | Q24: 794 | R24: 38 | S24: 3
H25: Grand Total | I25: 1500 | J25: 437771 | K25: 291.84733 | L25: 36963 | M25: 0.084434556 | P25: B-25622 | Q25: 534 | R25: 0 | S25: 1
P26: B-25623 | Q26: 465 | R26: 3 | S26: 4
P27: B-25624 | Q27: 26 | R27: 12 | S27: 1
P28: B-25625 | Q28: 791 | R28: -350 | S28: 3
P29: B-25626 | Q29: 1149 | R29: 262 | S29: 2
P30: B-25627 | Q30: 55 | R30: -39 | S30: 1
P31: B-25628 | Q31: 299 | R31: -4 | S31: 3
P32: B-25629 | Q32: 1560 | R32: 421 | S32: 1
P33: B-25630 | Q33: 506 | R33: -211 | S33: 6
P34: B-25631 | Q34: 89 | R34: -89 | S34: 1
P35: B-25632 | Q35: 19 | R35: -2 | S35: 1
P36: B-25633 | Q36: 1456 | R36: -217 | S36: 3
P37: B-25634 | Q37: 389 | R37: -83 | S37: 1
... P504: Grand Total | Q504: 437771 | R504: 36963 | S504: 1500

Sheet Details_cleaned_work
A1: order_id | B1: amount | C1: profit | D1: quantity | E1: category | F1: sub_category | G1: payment_mode
A2: B-25681 | B2: 1096 | C2: 658 | D2: 7 | E2: Electronics | F2: Electronic Games | G2: COD
A3: B-26055 | B3: 5729 | C3: 64 | D3: 14 | E3: Furniture | F3: Chairs | G3: EMI
A4: B-25955 | B4: 2927 | C4: 146 | D4: 8 | E4: Furniture | F4: Bookcases | G4: EMI
A5: B-26093 | B5: 2847 | C5: 712 | D5: 8 | E5: Electronics | F5: Printers | G5: Credit Card
A6: B-25602 | B6: 2617 | C6: 1151 | D6: 4 | E6: Electronics | F6: Phones | G6: Credit Card
A7: B-25881 | B7: 2244 | C7: 247 | D7: 4 | E7: Clothing | F7: Trousers | G7: Credit Card
A8: B-25696 | B8: 275 | C8: -275 | D8: 4 | E8: Clothing | F8: Saree | G8: COD
A9: B-25687 | B9: 387 | C9: -213 | D9: 5 | E9: Clothing | F9: Saree | G9: UPI
A10: B-25643 | B10: 50 | C10: -44 | D10: 2 | E10: Clothing | F10: Handkerchief | G10: UPI
A11: B-25851 | B11: 135 | C11: -54 | D11: 5 | E11: Clothing | F11: Kurti | G11: COD
A12: B-25703 | B12: 231 | C12: -190 | D12: 9 | E12: Clothing | F12: Handkerchief | G12: COD
A13: B-25887 | B13: 2125 | C13: -234 | D13: 6 | E13: Electronics | F13: Printers | G13: EMI
... A1501: B-25993 | B1501: 4363 | C1501: 305 | D1501: 5 | E1501: Furniture | F1501: Tables | G1501: EMI

Sheet Details_cleaned
A1: order_id | B1: amount | C1: profit | D1: quantity | E1: category | F1: sub_category | G1: payment_mode
A2: B-25681 | B2: 1096 | C2: 658 | D2: 7 | E2: Electronics | F2: Electronic Games | G2: COD
A3: B-26055 | B3: 5729 | C3: 64 | D3: 14 | E3: Furniture | F3: Chairs | G3: EMI
A4: B-25955 | B4: 2927 | C4: 146 | D4: 8 | E4: Furniture | F4: Bookcases | G4: EMI
A5: B-26093 | B5: 2847 | C5: 712 | D5: 8 | E5: Electronics | F5: Printers | G5: Credit Card
A6: B-25602 | B6: 2617 | C6: 1151 | D6: 4 | E6: Electronics | F6: Phones | G6: Credit Card
A7: B-25881 | B7: 2244 | C7: 247 | D7: 4 | E7: Clothing | F7: Trousers | G7: Credit Card
A8: B-25696 | B8: 275 | C8: -275 | D8: 4 | E8: Clothing | F8: Saree | G8: COD
A9: B-25687 | B9: 387 | C9: -213 | D9: 5 | E9: Clothing | F9: Saree | G9: UPI
A10: B-25643 | B10: 50 | C10: -44 | D10: 2 | E10: Clothing | F10: Handkerchief | G10: UPI
A11: B-25851 | B11: 135 | C11: -54 | D11: 5 | E11: Clothing | F11: Kurti | G11: COD
A12: B-25703 | B12: 231 | C12: -190 | D12: 9 | E12: Clothing | F12: Handkerchief | G12: COD
A13: B-25887 | B13: 2125 | C13: -234 | D13: 6 | E13: Electronics | F13: Printers | G13: EMI
... A1501: B-25993 | B1501: 4363 | C1501: 305 | D1501: 5 | E1501: Furniture | F1501: Tables | G1501: EMI

Sheet Data_Quality_Report
A2: {=_xlfn.SEQUENCE(10)} -> 1 | B2: The data was visually scanned for data quality issues of which none was seen or observed
A3: 2 | B3: The sheet was duplicated in order to preserve the initial dataset incase of future problems and renamed "Data_cleaned_work"
A4: 3 | B4: The dataset was then converted to an excel table then another visual scan was done this time with the help for filters
A5: 4 | B5: From the readme provided, it show that the dataset was already cleaned, and after visual scan, I confirmed that
A6: 5 | B6: Data types for amount and profit was changed to currency and that of quantity was changed to number
A7: 6 | B7: A new sheet "Calculations was created to calculate metrics
A8: 7 | B8: A new sheet was created "Pivot Tables" to easily identipy profit and loss indicatos
A9: 8 | B9: A new sheet "PT_Chart" was created to create pivot table charts to be represented on the dashboard
A10: 9 | B10: A new sheet for dashboard was created
A11: 10 | B11: A snew sheet for summary, insights and recommendations was created.
